paddle_billing_client/__init__.py
paddle_billing_client/client.py
paddle_billing_client/endpoints.py
paddle_billing_client/errors.py
paddle_billing_client/formatters.py
paddle_billing_client/helpers.py
paddle_billing_client/models/__init__.py
paddle_billing_client/models/address.py
paddle_billing_client/models/adjustment.py
paddle_billing_client/models/base.py
paddle_billing_client/models/business.py
paddle_billing_client/models/common.py
paddle_billing_client/models/customer.py
paddle_billing_client/models/discount.py
paddle_billing_client/models/event.py
paddle_billing_client/models/notification.py
paddle_billing_client/models/notification_setting.py
paddle_billing_client/models/price.py
paddle_billing_client/models/product.py
paddle_billing_client/models/subscription.py
paddle_billing_client/models/transaction.py
paddle_billing_client/pagination.py
paddle_billing_client/utils.py
paddle_billing_client-0.2.19.dist-info/LICENSE
paddle_billing_client-0.2.19.dist-info/METADATA
paddle_billing_client-0.2.19.dist-info/WHEEL
paddle_billing_client-0.2.19.dist-info/RECORD
