Metadata-Version: 2.1
Name: paddle-billing-client
Version: 0.2.19
Summary: Python wrapper around the new Paddle Billing API
Home-page: https://github.com/websideproject/paddle-billing-client
License: MIT
Author: Benjamin Gervan
Author-email: bgervan@webstormit.com
Requires-Python: >=3.9,<4.0
Classifier: Development Status :: 3 - Alpha
Classifier: Intended Audience :: Developers
Classifier: License :: OSI Approved :: MIT License
Classifier: Operating System :: OS Independent
Classifier: Programming Language :: Python :: 3
Classifier: Programming Language :: Python :: 3.9
Classifier: Programming Language :: Python :: 3.10
Classifier: Programming Language :: Python :: 3.11
Classifier: Programming Language :: Python :: 3.7
Classifier: Programming Language :: Python :: 3.8
Classifier: Topic :: Software Development :: Libraries :: Python Modules
Requires-Dist: api-client-pydantic (>=3.1.0,<4.0.0)
Requires-Dist: importlib_metadata (>=4.5.0,<5.0.0) ; python_version < "3.8"
Requires-Dist: pydantic (>=2.0,<=2.10.6)
Project-URL: Repository, https://github.com/websideproject/paddle-billing-client
